scope/__init__.py
scope/cli.py
scope/commands/__init__.py
scope/commands/abort.py
scope/commands/poll.py
scope/commands/setup.py
scope/commands/spawn.py
scope/commands/trajectory.py
scope/commands/uninstall.py
scope/commands/update.py
scope/commands/wait.py
scope/core/__init__.py
scope/core/abort.py
scope/core/config.py
scope/core/contract.py
scope/core/dag.py
scope/core/project.py
scope/core/session.py
scope/core/state.py
scope/core/tmux.py
scope/hooks/__init__.py
scope/hooks/handler.py
scope/hooks/install.py
scope/tui/__init__.py
scope/tui/app.py
scope/tui/screens/__init__.py
scope/tui/widgets/__init__.py
scope/tui/widgets/session_tree.py
scopeai-0.1.5.dist-info/METADATA
scopeai-0.1.5.dist-info/WHEEL
scopeai-0.1.5.dist-info/entry_points.txt
scopeai-0.1.5.dist-info/licenses/LICENSE
scopeai-0.1.5.dist-info/RECORD
