Metadata-Version: 2.4
Name: scopeai
Version: 0.1.5
Summary: Subagent orchestration for Claude Code
Project-URL: Homepage, https://github.com/adagradschool/scope
Project-URL: Repository, https://github.com/adagradschool/scope
Project-URL: Issues, https://github.com/adagradschool/scope/issues
Author: ada
License: MIT
License-File: LICENSE
Keywords: agent,ai,automation,claude,claude-code,llm,orchestration,subagent
Classifier: Development Status :: 3 - Alpha
Classifier: Environment :: Console
Classifier: Intended Audience :: Developers
Classifier: License :: OSI Approved :: MIT License
Classifier: Operating System :: OS Independent
Classifier: Programming Language :: Python :: 3
Classifier: Programming Language :: Python :: 3.10
Classifier: Programming Language :: Python :: 3.11
Classifier: Programming Language :: Python :: 3.12
Classifier: Programming Language :: Python :: 3.13
Classifier: Topic :: Software Development :: Libraries :: Python Modules
Classifier: Topic :: Utilities
Classifier: Typing :: Typed
Requires-Python: >=3.10
Requires-Dist: click>=8.0.0
Requires-Dist: orjson>=3.9.0
Requires-Dist: textual>=0.50.0
Requires-Dist: watchfiles>=0.21.0
